nonebot_plugin_prometheus/__init__.py
nonebot_plugin_prometheus/api.py
nonebot_plugin_prometheus/config.py
nonebot_plugin_prometheus/extension.py
nonebot_plugin_prometheus/formatter.py
nonebot_plugin_prometheus/metrics.py
nonebot_plugin_prometheus/query.py
nonebot_plugin_prometheus/registry.py
nonebot_plugin_prometheus/utils.py
nonebot_plugin_prometheus/matcher/__init__.py
nonebot_plugin_prometheus/matcher/metrics_query.py
nonebot_plugin_prometheus/matcher/test_matcher.py
nonebot_plugin_prometheus-0.4.1.dist-info/METADATA
nonebot_plugin_prometheus-0.4.1.dist-info/WHEEL
nonebot_plugin_prometheus-0.4.1.dist-info/licenses/LICENSE
nonebot_plugin_prometheus-0.4.1.dist-info/RECORD
