Metadata-Version: 2.4
Name: nonebot-plugin-prometheus
Version: 0.4.1
Summary: 为 NoneBot 和其他插件提供 Prometheus 监控支持
Project-URL: Homepage, https://github.com/suyiiyii/nonebot-plugin-prometheus
Project-URL: Repository, https://github.com/suyiiyii/nonebot-plugin-prometheus
Project-URL: Bug Tracker, https://github.com/suyiiyii/nonebot-plugin-prometheus/issues
Author-email: suyiiyii <suyiiyii@gmail.com>
Maintainer-email: suyiiyii <suyiiyii@gmail.com>
License: MIT License
License-File: LICENSE
Keywords: nonebot,nonebot-plugin,nonebot2,prometheus
Classifier: Development Status :: 5 - Production/Stable
Classifier: Intended Audience :: Developers
Classifier: License :: OSI Approved :: MIT License
Classifier: Operating System :: OS Independent
Classifier: Programming Language :: Python :: 3
Classifier: Programming Language :: Python :: 3.9
Classifier: Programming Language :: Python :: 3.10
Classifier: Programming Language :: Python :: 3.11
Classifier: Programming Language :: Python :: 3.12
Classifier: Programming Language :: Python :: 3.13
Classifier: Topic :: Software Development :: Libraries
Requires-Python: <4.0,>=3.9
Requires-Dist: nonebot-plugin-alconna>=0.55.0
Requires-Dist: nonebot2>=2.2.1
Requires-Dist: prometheus-client>=0.21.1
